vinzy_splitter/__init__.py
vinzy_splitter-1.0.1.dist-info/LICENSE
vinzy_splitter-1.0.1.dist-info/METADATA
vinzy_splitter-1.0.1.dist-info/WHEEL
vinzy_splitter-1.0.1.dist-info/top_level.txt
vinzy_splitter-1.0.1.dist-info/RECORD
