Metadata-Version: 2.1
Name: vinzy-splitter
Version: 1.0.1
Summary: A package will help you to split your data frame into training, validation and testing subsets
Home-page: https://github.com/vinayak-97/Training-Validation-and-Testing-dataframe-splitter-package.git
Author: Vinayak Bhosale
Author-email: vinubhosale.cj@gmail.com
License: MIT
Platform: UNKNOWN
Classifier: License :: OSI Approved :: MIT License
Classifier: Programming Language :: Python :: 3
Classifier: Programming Language :: Python :: 3.7
Classifier: Programming Language :: Python :: 3.8
Requires-Dist: numpy
Requires-Dist: pandas
